distanceloss/__init__.py
distanceloss/distance_loss.py
distance_loss_torch-0.1.0.dist-info/LICENSE
distance_loss_torch-0.1.0.dist-info/METADATA
distance_loss_torch-0.1.0.dist-info/WHEEL
distance_loss_torch-0.1.0.dist-info/top_level.txt
distance_loss_torch-0.1.0.dist-info/RECORD
